fpyjp/__init__.py
fpyjp/conf/__init__.py
fpyjp/core/__init__.py
fpyjp/core/balance_simulator.py
fpyjp/core/interest_factor.py
fpyjp/core/loan_simulator.py
fpyjp/schemas/__init__.py
fpyjp/schemas/balance.py
fpyjp/schemas/cashflow.py
fpyjp/schemas/loan.py
fpyjp/utils/__init__.py
fpyjp/utils/list_utils.py
fpyjp/utils/math_utils.py
fpyjp-0.0.7.dist-info/METADATA
fpyjp-0.0.7.dist-info/WHEEL
fpyjp-0.0.7.dist-info/licenses/LICENSE
fpyjp-0.0.7.dist-info/RECORD
