Metadata-Version: 2.4
Name: fpyjp
Version: 0.0.7
Summary: FPy-JP - Financial Planning in Python (Based on the Japanese System)
Project-URL: Homepage, https://github.com/well-living/FPy
Project-URL: Bug Tracker, https://github.com/well-living/FPy/issues
Project-URL: Source, https://github.com/well-living/FPy
Author: well-living
License: MIT
License-File: LICENSE
Classifier: Development Status :: 4 - Beta
Classifier: License :: OSI Approved :: MIT License
Classifier: Programming Language :: Python :: 3.12
Requires-Python: >=3.12
